conf/__init__.py
conf/asgi.py
conf/settings.py
conf/urls.py
conf/wsgi.py
django_helper/__init__.py
django_helper/code.py
django_helper/test.py
django_helper/tests/__init__.py
django_helper/tests/test_assert.py
django_helper/tests/test_code.py
django_sca_helper-0.2.0.dist-info/LICENSE
django_sca_helper-0.2.0.dist-info/METADATA
django_sca_helper-0.2.0.dist-info/WHEEL
django_sca_helper-0.2.0.dist-info/top_level.txt
django_sca_helper-0.2.0.dist-info/RECORD
